LICENSE
README.md
setup.py
prljavtk/__init__.py
prljavtk/prljavtk.py
prljavtk.egg-info/PKG-INFO
prljavtk.egg-info/SOURCES.txt
prljavtk.egg-info/dependency_links.txt
prljavtk.egg-info/entry_points.txt
prljavtk.egg-info/requires.txt
prljavtk.egg-info/top_level.txt